{"264445053596991498":{"prefix":"","desc":"","muteRole":"","autoRole":"","selfAssignRoles":[],"joinChanels":[],"joinType":"","joinMsg":"","joinDM":false,"byeChannels":[],"byeType":"","byeMsg":"","byeDM":false,"currency":"","xpSystem":true,"lvlUpMsg":"","channelCreate":false,"channelDelete":false,"channelUpdate":false,"guildBanAdd":false,"guildBanRemove":false,"userUpdate":false,"roleCreate":false,"roleDelete":false,"roleUpdate":false,"logChannels":[],"disabledCmds":[],"disabledMdls":[],"disabledAllMdls":false,"blacklistedUsers":[],"badWords":[]},"290162830009696257":{"prefix":"","desc":"","muteRole":"","autoRole":"","selfAssignRoles":[],"joinChanels":[],"joinType":"","joinMsg":"","joinDM":false,"byeChannels":[],"byeType":"","byeMsg":"","byeDM":false,"currency":"","xpSystem":true,"lvlUpMsg":"","channelCreate":false,"channelDelete":false,"channelUpdate":false,"guildBanAdd":false,"guildBanRemove":false,"userUpdate":false,"roleCreate":false,"roleDelete":false,"roleUpdate":false,"logChannels":[],"disabledCmds":[],"disabledMdls":[],"disabledAllMdls":false,"blacklistedUsers":[],"badWords":[]},"110373943822540800":{"prefix":"","desc":"","muteRole":"","autoRole":"","selfAssignRoles":[],"joinChanels":[],"joinType":"","joinMsg":"","joinDM":false,"byeChannels":[],"byeType":"","byeMsg":"","byeDM":false,"currency":"","xpSystem":true,"lvlUpMsg":"","channelCreate":false,"channelDelete":false,"channelUpdate":false,"guildBanAdd":false,"guildBanRemove":false,"userUpdate":false,"roleCreate":false,"roleDelete":false,"roleUpdate":false,"logChannels":[],"disabledCmds":[],"disabledMdls":[],"disabledAllMdls":false,"blacklistedUsers":[],"badWords":[]},"318684647284539415":{"prefix":"","desc":"","muteRole":"","autoRole":"","selfAssignRoles":[],"joinChanels":[],"joinType":"","joinMsg":"","joinDM":false,"byeChannels":[],"byeType":"","byeMsg":"","byeDM":false,"currency":"","xpSystem":true,"lvlUpMsg":"","channelCreate":false,"channelDelete":false,"channelUpdate":false,"guildBanAdd":false,"guildBanRemove":false,"userUpdate":false,"roleCreate":false,"roleDelete":false,"roleUpdate":false,"logChannels":[],"disabledCmds":[],"disabledMdls":[],"disabledAllMdls":false,"blacklistedUsers":[],"badWords":[]},"341965407680462859":{"prefix":"","desc":"","muteRole":"","autoRole":"","selfAssignRoles":[],"joinChanels":[],"joinType":"","joinMsg":"","joinDM":false,"byeChannels":[],"byeType":"","byeMsg":"","byeDM":false,"currency":"","xpSystem":true,"lvlUpMsg":"","channelCreate":false,"channelDelete":false,"channelUpdate":false,"guildBanAdd":false,"guildBanRemove":false,"userUpdate":false,"roleCreate":false,"roleDelete":false,"roleUpdate":false,"logChannels":[],"disabledCmds":[],"disabledMdls":[],"disabledAllMdls":false,"blacklistedUsers":[],"badWords":[]},"353961611825774592":{"prefix":"","desc":"","muteRole":"","autoRole":"","selfAssignRoles":[],"joinChanels":[],"joinType":"","joinMsg":"","joinDM":false,"byeChannels":[],"byeType":"","byeMsg":"","byeDM":false,"currency":"","xpSystem":true,"lvlUpMsg":"","channelCreate":false,"channelDelete":false,"channelUpdate":false,"guildBanAdd":false,"guildBanRemove":false,"userUpdate":false,"roleCreate":false,"roleDelete":false,"roleUpdate":false,"logChannels":[],"disabledCmds":[],"disabledMdls":[],"disabledAllMdls":false,"blacklistedUsers":[],"badWords":[]},"363258302177476608":{"prefix":"","desc":"","muteRole":"","autoRole":"","selfAssignRoles":[],"joinChanels":[],"joinType":"","joinMsg":"","joinDM":false,"byeChannels":[],"byeType":"","byeMsg":"","byeDM":false,"currency":"","xpSystem":true,"lvlUpMsg":"","channelCreate":false,"channelDelete":false,"channelUpdate":false,"guildBanAdd":false,"guildBanRemove":false,"userUpdate":false,"roleCreate":false,"roleDelete":false,"roleUpdate":false,"logChannels":[],"disabledCmds":[],"disabledMdls":[],"disabledAllMdls":false,"blacklistedUsers":[],"badWords":[]},"331632569563217920":{"prefix":"","desc":"","muteRole":"","autoRole":"","selfAssignRoles":[],"joinChanels":[],"joinType":"","joinMsg":"","joinDM":false,"byeChannels":[],"byeType":"","byeMsg":"","byeDM":false,"currency":"","xpSystem":true,"lvlUpMsg":"","channelCreate":false,"channelDelete":false,"channelUpdate":false,"guildBanAdd":false,"guildBanRemove":false,"userUpdate":false,"roleCreate":false,"roleDelete":false,"roleUpdate":false,"logChannels":[],"disabledCmds":[],"disabledMdls":[],"disabledAllMdls":false,"blacklistedUsers":[],"badWords":[]},"363006336864354317":{"prefix":"","desc":"","muteRole":"","autoRole":"","selfAssignRoles":[],"joinChanels":[],"joinType":"","joinMsg":"","joinDM":false,"byeChannels":[],"byeType":"","byeMsg":"","byeDM":false,"currency":"","xpSystem":true,"lvlUpMsg":"","channelCreate":false,"channelDelete":false,"channelUpdate":false,"guildBanAdd":false,"guildBanRemove":false,"userUpdate":false,"roleCreate":false,"roleDelete":false,"roleUpdate":false,"logChannels":[],"disabledCmds":[],"disabledMdls":[],"disabledAllMdls":false,"blacklistedUsers":[],"badWords":[]},"269240782379155457":{"prefix":"","desc":"","muteRole":"","autoRole":"","selfAssignRoles":[],"joinChanels":[],"joinType":"","joinMsg":"","joinDM":false,"byeChannels":[],"byeType":"","byeMsg":"","byeDM":false,"currency":"","xpSystem":true,"lvlUpMsg":"","channelCreate":false,"channelDelete":false,"channelUpdate":false,"guildBanAdd":false,"guildBanRemove":false,"userUpdate":false,"roleCreate":false,"roleDelete":false,"roleUpdate":false,"logChannels":[],"disabledCmds":[],"disabledMdls":[],"disabledAllMdls":false,"blacklistedUsers":[],"badWords":[]},"340992570060570635":{"prefix":"","desc":"","muteRole":"","autoRole":"","selfAssignRoles":[],"joinChanels":[],"joinType":"","joinMsg":"","joinDM":false,"byeChannels":[],"byeType":"","byeMsg":"","byeDM":false,"currency":"","xpSystem":true,"lvlUpMsg":"","channelCreate":false,"channelDelete":false,"channelUpdate":false,"guildBanAdd":false,"guildBanRemove":false,"userUpdate":false,"roleCreate":false,"roleDelete":false,"roleUpdate":false,"logChannels":[],"disabledCmds":[],"disabledMdls":[],"disabledAllMdls":false,"blacklistedUsers":[],"badWords":[]},"329662255962783744":{"prefix":"","desc":"","muteRole":"","autoRole":"","selfAssignRoles":[],"joinChanels":[],"joinType":"","joinMsg":"","joinDM":false,"byeChannels":[],"byeType":"","byeMsg":"","byeDM":false,"currency":"","xpSystem":true,"lvlUpMsg":"","channelCreate":false,"channelDelete":false,"channelUpdate":false,"guildBanAdd":false,"guildBanRemove":false,"userUpdate":false,"roleCreate":false,"roleDelete":false,"roleUpdate":false,"logChannels":[],"disabledCmds":[],"disabledMdls":[],"disabledAllMdls":false,"blacklistedUsers":[],"badWords":[]},"352676231247822849":{"prefix":"","desc":"","muteRole":"","autoRole":"","selfAssignRoles":[],"joinChanels":[],"joinType":"","joinMsg":"","joinDM":false,"byeChannels":[],"byeType":"","byeMsg":"","byeDM":false,"currency":"","xpSystem":true,"lvlUpMsg":"","channelCreate":false,"channelDelete":false,"channelUpdate":false,"guildBanAdd":false,"guildBanRemove":false,"userUpdate":false,"roleCreate":false,"roleDelete":false,"roleUpdate":false,"logChannels":[],"disabledCmds":[],"disabledMdls":[],"disabledAllMdls":false,"blacklistedUsers":[],"badWords":[]},"324539249129029632":{"prefix":"","desc":"","muteRole":"","autoRole":"","selfAssignRoles":[],"joinChanels":[],"joinType":"","joinMsg":"","joinDM":false,"byeChannels":[],"byeType":"","byeMsg":"","byeDM":false,"currency":"","xpSystem":true,"lvlUpMsg":"","channelCreate":false,"channelDelete":false,"channelUpdate":false,"guildBanAdd":false,"guildBanRemove":false,"userUpdate":false,"roleCreate":false,"roleDelete":false,"roleUpdate":false,"logChannels":[],"disabledCmds":[],"disabledMdls":[],"disabledAllMdls":false,"blacklistedUsers":[],"badWords":[]},"342651403912609792":{"prefix":"","desc":"","muteRole":"","autoRole":"","selfAssignRoles":[],"joinChanels":[],"joinType":"","joinMsg":"","joinDM":false,"byeChannels":[],"byeType":"","byeMsg":"","byeDM":false,"currency":"","xpSystem":true,"lvlUpMsg":"","channelCreate":false,"channelDelete":false,"channelUpdate":false,"guildBanAdd":false,"guildBanRemove":false,"userUpdate":false,"roleCreate":false,"roleDelete":false,"roleUpdate":false,"logChannels":[],"disabledCmds":[],"disabledMdls":[],"disabledAllMdls":false,"blacklistedUsers":[],"badWords":[]},"347420559472066571":{"prefix":"","desc":"","muteRole":"","autoRole":"","selfAssignRoles":[],"joinChanels":[],"joinType":"","joinMsg":"","joinDM":false,"byeChannels":[],"byeType":"","byeMsg":"","byeDM":false,"currency":"","xpSystem":true,"lvlUpMsg":"","channelCreate":false,"channelDelete":false,"channelUpdate":false,"guildBanAdd":false,"guildBanRemove":false,"userUpdate":false,"roleCreate":false,"roleDelete":false,"roleUpdate":false,"logChannels":[],"disabledCmds":[],"disabledMdls":[],"disabledAllMdls":false,"blacklistedUsers":[],"badWords":[]},"312060523501846530":{"prefix":"","desc":"","muteRole":"","autoRole":"","selfAssignRoles":[],"joinChanels":[],"joinType":"","joinMsg":"","joinDM":false,"byeChannels":[],"byeType":"","byeMsg":"","byeDM":false,"currency":"","xpSystem":true,"lvlUpMsg":"","channelCreate":false,"channelDelete":false,"channelUpdate":false,"guildBanAdd":false,"guildBanRemove":false,"userUpdate":false,"roleCreate":false,"roleDelete":false,"roleUpdate":false,"logChannels":[],"disabledCmds":[],"disabledMdls":[],"disabledAllMdls":false,"blacklistedUsers":[],"badWords":[]},"346078702230044672":{"prefix":"","desc":"","muteRole":"","autoRole":"","selfAssignRoles":[],"joinChanels":[],"joinType":"","joinMsg":"","joinDM":false,"byeChannels":[],"byeType":"","byeMsg":"","byeDM":false,"currency":"","xpSystem":true,"lvlUpMsg":"","channelCreate":false,"channelDelete":false,"channelUpdate":false,"guildBanAdd":false,"guildBanRemove":false,"userUpdate":false,"roleCreate":false,"roleDelete":false,"roleUpdate":false,"logChannels":[],"disabledCmds":[],"disabledMdls":[],"disabledAllMdls":false,"blacklistedUsers":[],"badWords":[]},"333214106683441152":{"prefix":"","desc":"","muteRole":"","autoRole":"","selfAssignRoles":[],"joinChanels":[],"joinType":"","joinMsg":"","joinDM":false,"byeChannels":[],"byeType":"","byeMsg":"","byeDM":false,"currency":"","xpSystem":true,"lvlUpMsg":"","channelCreate":false,"channelDelete":false,"channelUpdate":false,"guildBanAdd":false,"guildBanRemove":false,"userUpdate":false,"roleCreate":false,"roleDelete":false,"roleUpdate":false,"logChannels":[],"disabledCmds":[],"disabledMdls":[],"disabledAllMdls":false,"blacklistedUsers":[],"badWords":[]},"363686114273263617":{"prefix":"","desc":"","muteRole":"","autoRole":"","selfAssignRoles":[],"joinChanels":[],"joinType":"","joinMsg":"","joinDM":false,"byeChannels":[],"byeType":"","byeMsg":"","byeDM":false,"currency":"","xpSystem":true,"lvlUpMsg":"","channelCreate":false,"channelDelete":false,"channelUpdate":false,"guildBanAdd":false,"guildBanRemove":false,"userUpdate":false,"roleCreate":false,"roleDelete":false,"roleUpdate":false,"logChannels":[],"disabledCmds":[],"disabledMdls":[],"disabledAllMdls":false,"blacklistedUsers":[],"badWords":[]},"310832708890918914":{"prefix":"","desc":"","muteRole":"","autoRole":"","selfAssignRoles":[],"joinChanels":[],"joinType":"","joinMsg":"","joinDM":false,"byeChannels":[],"byeType":"","byeMsg":"","byeDM":false,"currency":"","xpSystem":true,"lvlUpMsg":"","channelCreate":false,"channelDelete":false,"channelUpdate":false,"guildBanAdd":false,"guildBanRemove":false,"userUpdate":false,"roleCreate":false,"roleDelete":false,"roleUpdate":false,"logChannels":[],"disabledCmds":[],"disabledMdls":[],"disabledAllMdls":false,"blacklistedUsers":[],"badWords":[]},"292395307764023296":{"prefix":"","desc":"","muteRole":"","autoRole":"","selfAssignRoles":[],"joinChanels":[],"joinType":"","joinMsg":"","joinDM":false,"byeChannels":[],"byeType":"","byeMsg":"","byeDM":false,"currency":"","xpSystem":true,"lvlUpMsg":"","channelCreate":false,"channelDelete":false,"channelUpdate":false,"guildBanAdd":false,"guildBanRemove":false,"userUpdate":false,"roleCreate":false,"roleDelete":false,"roleUpdate":false,"logChannels":[],"disabledCmds":[],"disabledMdls":[],"disabledAllMdls":false,"blacklistedUsers":[],"badWords":[]},"293514195025133568":{"prefix":"","desc":"","muteRole":"","autoRole":"","selfAssignRoles":[],"joinChanels":[],"joinType":"","joinMsg":"","joinDM":false,"byeChannels":[],"byeType":"","byeMsg":"","byeDM":false,"currency":"","xpSystem":true,"lvlUpMsg":"","channelCreate":false,"channelDelete":false,"channelUpdate":false,"guildBanAdd":false,"guildBanRemove":false,"userUpdate":false,"roleCreate":false,"roleDelete":false,"roleUpdate":false,"logChannels":[],"disabledCmds":[],"disabledMdls":[],"disabledAllMdls":false,"blacklistedUsers":[],"badWords":[]},"342029414026051586":{"prefix":"","desc":"","muteRole":"","autoRole":"","selfAssignRoles":[],"joinChanels":[],"joinType":"","joinMsg":"","joinDM":false,"byeChannels":[],"byeType":"","byeMsg":"","byeDM":false,"currency":"","xpSystem":true,"lvlUpMsg":"","channelCreate":false,"channelDelete":false,"channelUpdate":false,"guildBanAdd":false,"guildBanRemove":false,"userUpdate":false,"roleCreate":false,"roleDelete":false,"roleUpdate":false,"logChannels":[],"disabledCmds":[],"disabledMdls":[],"disabledAllMdls":false,"blacklistedUsers":[],"badWords":[]},"356841822854840321":{"prefix":"","desc":"","muteRole":"","autoRole":"","selfAssignRoles":[],"joinChanels":[],"joinType":"","joinMsg":"","joinDM":false,"byeChannels":[],"byeType":"","byeMsg":"","byeDM":false,"currency":"","xpSystem":true,"lvlUpMsg":"","channelCreate":false,"channelDelete":false,"channelUpdate":false,"guildBanAdd":false,"guildBanRemove":false,"userUpdate":false,"roleCreate":false,"roleDelete":false,"roleUpdate":false,"logChannels":[],"disabledCmds":[],"disabledMdls":[],"disabledAllMdls":false,"blacklistedUsers":[],"badWords":[]},"360949955826810880":{"prefix":"","desc":"","muteRole":"","autoRole":"","selfAssignRoles":[],"joinChanels":[],"joinType":"","joinMsg":"","joinDM":false,"byeChannels":[],"byeType":"","byeMsg":"","byeDM":false,"currency":"","xpSystem":true,"lvlUpMsg":"","channelCreate":false,"channelDelete":false,"channelUpdate":false,"guildBanAdd":false,"guildBanRemove":false,"userUpdate":false,"roleCreate":false,"roleDelete":false,"roleUpdate":false,"logChannels":[],"disabledCmds":[],"disabledMdls":[],"disabledAllMdls":false,"blacklistedUsers":[],"badWords":[]},"352937817065914371":{"prefix":"","desc":"","muteRole":"","autoRole":"","selfAssignRoles":[],"joinChanels":[],"joinType":"","joinMsg":"","joinDM":false,"byeChannels":[],"byeType":"","byeMsg":"","byeDM":false,"currency":"","xpSystem":true,"lvlUpMsg":"","channelCreate":false,"channelDelete":false,"channelUpdate":false,"guildBanAdd":false,"guildBanRemove":false,"userUpdate":false,"roleCreate":false,"roleDelete":false,"roleUpdate":false,"logChannels":[],"disabledCmds":[],"disabledMdls":[],"disabledAllMdls":false,"blacklistedUsers":[],"badWords":[]},"362358646337830912":{"prefix":"","desc":"","muteRole":"","autoRole":"","selfAssignRoles":[],"joinChanels":[],"joinType":"","joinMsg":"","joinDM":false,"byeChannels":[],"byeType":"","byeMsg":"","byeDM":false,"currency":"","xpSystem":true,"lvlUpMsg":"","channelCreate":false,"channelDelete":false,"channelUpdate":false,"guildBanAdd":false,"guildBanRemove":false,"userUpdate":false,"roleCreate":false,"roleDelete":false,"roleUpdate":false,"logChannels":[],"disabledCmds":[],"disabledMdls":[],"disabledAllMdls":false,"blacklistedUsers":[],"badWords":[]},"267767210317971458":{"prefix":"","desc":"","muteRole":"","autoRole":"","selfAssignRoles":[],"joinChanels":[],"joinType":"","joinMsg":"","joinDM":false,"byeChannels":[],"byeType":"","byeMsg":"","byeDM":false,"currency":"","xpSystem":true,"lvlUpMsg":"","channelCreate":false,"channelDelete":false,"channelUpdate":false,"guildBanAdd":false,"guildBanRemove":false,"userUpdate":false,"roleCreate":false,"roleDelete":false,"roleUpdate":false,"logChannels":[],"disabledCmds":[],"disabledMdls":[],"disabledAllMdls":false,"blacklistedUsers":[],"badWords":[]},"356086938723287042":{"prefix":"","desc":"","muteRole":"","autoRole":"","selfAssignRoles":[],"joinChanels":[],"joinType":"","joinMsg":"","joinDM":false,"byeChannels":[],"byeType":"","byeMsg":"","byeDM":false,"currency":"","xpSystem":true,"lvlUpMsg":"","channelCreate":false,"channelDelete":false,"channelUpdate":false,"guildBanAdd":false,"guildBanRemove":false,"userUpdate":false,"roleCreate":false,"roleDelete":false,"roleUpdate":false,"logChannels":[],"disabledCmds":[],"disabledMdls":[],"disabledAllMdls":false,"blacklistedUsers":[],"badWords":[]},"290195358280056833":{"prefix":"","desc":"","muteRole":"","autoRole":"","selfAssignRoles":[],"joinChanels":[],"joinType":"","joinMsg":"","joinDM":false,"byeChannels":[],"byeType":"","byeMsg":"","byeDM":false,"currency":"","xpSystem":true,"lvlUpMsg":"","channelCreate":false,"channelDelete":false,"channelUpdate":false,"guildBanAdd":false,"guildBanRemove":false,"userUpdate":false,"roleCreate":false,"roleDelete":false,"roleUpdate":false,"logChannels":[],"disabledCmds":[],"disabledMdls":[],"disabledAllMdls":false,"blacklistedUsers":[],"badWords":[]},"359097316864688131":{"prefix":"","desc":"","muteRole":"","autoRole":"","selfAssignRoles":[],"joinChanels":[],"joinType":"","joinMsg":"","joinDM":false,"byeChannels":[],"byeType":"","byeMsg":"","byeDM":false,"currency":"","xpSystem":true,"lvlUpMsg":"","channelCreate":false,"channelDelete":false,"channelUpdate":false,"guildBanAdd":false,"guildBanRemove":false,"userUpdate":false,"roleCreate":false,"roleDelete":false,"roleUpdate":false,"logChannels":[],"disabledCmds":[],"disabledMdls":[],"disabledAllMdls":false,"blacklistedUsers":[],"badWords":[]},"347350573340950528":{"prefix":"","desc":"","muteRole":"","autoRole":"","selfAssignRoles":[],"joinChanels":[],"joinType":"","joinMsg":"","joinDM":false,"byeChannels":[],"byeType":"","byeMsg":"","byeDM":false,"currency":"","xpSystem":true,"lvlUpMsg":"","channelCreate":false,"channelDelete":false,"channelUpdate":false,"guildBanAdd":false,"guildBanRemove":false,"userUpdate":false,"roleCreate":false,"roleDelete":false,"roleUpdate":false,"logChannels":[],"disabledCmds":[],"disabledMdls":[],"disabledAllMdls":false,"blacklistedUsers":[],"badWords":[]},"334105563854274572":{"prefix":"","desc":"","muteRole":"","autoRole":"","selfAssignRoles":[],"joinChanels":[],"joinType":"","joinMsg":"","joinDM":false,"byeChannels":[],"byeType":"","byeMsg":"","byeDM":false,"currency":"","xpSystem":true,"lvlUpMsg":"","channelCreate":false,"channelDelete":false,"channelUpdate":false,"guildBanAdd":false,"guildBanRemove":false,"userUpdate":false,"roleCreate":false,"roleDelete":false,"roleUpdate":false,"logChannels":[],"disabledCmds":[],"disabledMdls":[],"disabledAllMdls":false,"blacklistedUsers":[],"badWords":[]},"323227704612618240":{"prefix":"","desc":"","muteRole":"","autoRole":"","selfAssignRoles":[],"joinChanels":[],"joinType":"","joinMsg":"","joinDM":false,"byeChannels":[],"byeType":"","byeMsg":"","byeDM":false,"currency":"","xpSystem":true,"lvlUpMsg":"","channelCreate":false,"channelDelete":false,"channelUpdate":false,"guildBanAdd":false,"guildBanRemove":false,"userUpdate":false,"roleCreate":false,"roleDelete":false,"roleUpdate":false,"logChannels":[],"disabledCmds":[],"disabledMdls":[],"disabledAllMdls":false,"blacklistedUsers":[],"badWords":[]},"352154669193232387":{"prefix":"","desc":"","muteRole":"","autoRole":"","selfAssignRoles":[],"joinChanels":[],"joinType":"","joinMsg":"","joinDM":false,"byeChannels":[],"byeType":"","byeMsg":"","byeDM":false,"currency":"","xpSystem":true,"lvlUpMsg":"","channelCreate":false,"channelDelete":false,"channelUpdate":false,"guildBanAdd":false,"guildBanRemove":false,"userUpdate":false,"roleCreate":false,"roleDelete":false,"roleUpdate":false,"logChannels":[],"disabledCmds":[],"disabledMdls":[],"disabledAllMdls":false,"blacklistedUsers":[],"badWords":[]},"364030925828259844":{"prefix":"","desc":"","muteRole":"","autoRole":"","selfAssignRoles":[],"joinChanels":[],"joinType":"","joinMsg":"","joinDM":false,"byeChannels":[],"byeType":"","byeMsg":"","byeDM":false,"currency":"","xpSystem":true,"lvlUpMsg":"","channelCreate":false,"channelDelete":false,"channelUpdate":false,"guildBanAdd":false,"guildBanRemove":false,"userUpdate":false,"roleCreate":false,"roleDelete":false,"roleUpdate":false,"logChannels":[],"disabledCmds":[],"disabledMdls":[],"disabledAllMdls":false,"blacklistedUsers":[],"badWords":[]},"337667734709993482":{"prefix":"","desc":"","muteRole":"","autoRole":"","selfAssignRoles":[],"joinChanels":[],"joinType":"","joinMsg":"","joinDM":false,"byeChannels":[],"byeType":"","byeMsg":"","byeDM":false,"currency":"","xpSystem":true,"lvlUpMsg":"","channelCreate":false,"channelDelete":false,"channelUpdate":false,"guildBanAdd":false,"guildBanRemove":false,"userUpdate":false,"roleCreate":false,"roleDelete":false,"roleUpdate":false,"logChannels":[],"disabledCmds":[],"disabledMdls":[],"disabledAllMdls":false,"blacklistedUsers":[],"badWords":[]},"320059204461264906":{"prefix":"","desc":"","muteRole":"","autoRole":"","selfAssignRoles":[],"joinChanels":[],"joinType":"","joinMsg":"","joinDM":false,"byeChannels":[],"byeType":"","byeMsg":"","byeDM":false,"currency":"","xpSystem":true,"lvlUpMsg":"","channelCreate":false,"channelDelete":false,"channelUpdate":false,"guildBanAdd":false,"guildBanRemove":false,"userUpdate":false,"roleCreate":false,"roleDelete":false,"roleUpdate":false,"logChannels":[],"disabledCmds":[],"disabledMdls":[],"disabledAllMdls":false,"blacklistedUsers":[],"badWords":[]},"362649921322745866":{"prefix":"","desc":"","muteRole":"","autoRole":"","selfAssignRoles":[],"joinChanels":[],"joinType":"","joinMsg":"","joinDM":false,"byeChannels":[],"byeType":"","byeMsg":"","byeDM":false,"currency":"","xpSystem":true,"lvlUpMsg":"","channelCreate":false,"channelDelete":false,"channelUpdate":false,"guildBanAdd":false,"guildBanRemove":false,"userUpdate":false,"roleCreate":false,"roleDelete":false,"roleUpdate":false,"logChannels":[],"disabledCmds":[],"disabledMdls":[],"disabledAllMdls":false,"blacklistedUsers":[],"badWords":[]},"280448742950305803":{"prefix":"","desc":"","muteRole":"","autoRole":"","selfAssignRoles":[],"joinChanels":[],"joinType":"","joinMsg":"","joinDM":false,"byeChannels":[],"byeType":"","byeMsg":"","byeDM":false,"currency":"","xpSystem":true,"lvlUpMsg":"","channelCreate":false,"channelDelete":false,"channelUpdate":false,"guildBanAdd":false,"guildBanRemove":false,"userUpdate":false,"roleCreate":false,"roleDelete":false,"roleUpdate":false,"logChannels":[],"disabledCmds":[],"disabledMdls":[],"disabledAllMdls":false,"blacklistedUsers":[],"badWords":[]},"347768635353202690":{"prefix":"","desc":"","muteRole":"","autoRole":"","selfAssignRoles":[],"joinChanels":[],"joinType":"","joinMsg":"","joinDM":false,"byeChannels":[],"byeType":"","byeMsg":"","byeDM":false,"currency":"","xpSystem":true,"lvlUpMsg":"","channelCreate":false,"channelDelete":false,"channelUpdate":false,"guildBanAdd":false,"guildBanRemove":false,"userUpdate":false,"roleCreate":false,"roleDelete":false,"roleUpdate":false,"logChannels":[],"disabledCmds":[],"disabledMdls":[],"disabledAllMdls":false,"blacklistedUsers":[],"badWords":[]},"341218274060533772":{"prefix":"","desc":"","muteRole":"","autoRole":"","selfAssignRoles":[],"joinChanels":[],"joinType":"","joinMsg":"","joinDM":false,"byeChannels":[],"byeType":"","byeMsg":"","byeDM":false,"currency":"","xpSystem":true,"lvlUpMsg":"","channelCreate":false,"channelDelete":false,"channelUpdate":false,"guildBanAdd":false,"guildBanRemove":false,"userUpdate":false,"roleCreate":false,"roleDelete":false,"roleUpdate":false,"logChannels":[],"disabledCmds":[],"disabledMdls":[],"disabledAllMdls":false,"blacklistedUsers":[],"badWords":[]},"363126295217045505":{"prefix":"","desc":"","muteRole":"","autoRole":"","selfAssignRoles":[],"joinChanels":[],"joinType":"","joinMsg":"","joinDM":false,"byeChannels":[],"byeType":"","byeMsg":"","byeDM":false,"currency":"","xpSystem":true,"lvlUpMsg":"","channelCreate":false,"channelDelete":false,"channelUpdate":false,"guildBanAdd":false,"guildBanRemove":false,"userUpdate":false,"roleCreate":false,"roleDelete":false,"roleUpdate":false,"logChannels":[],"disabledCmds":[],"disabledMdls":[],"disabledAllMdls":false,"blacklistedUsers":[],"badWords":[]},"230764571151958019":{"prefix":"","desc":"","muteRole":"","autoRole":"","selfAssignRoles":[],"joinChanels":[],"joinType":"","joinMsg":"","joinDM":false,"byeChannels":[],"byeType":"","byeMsg":"","byeDM":false,"currency":"","xpSystem":true,"lvlUpMsg":"","channelCreate":false,"channelDelete":false,"channelUpdate":false,"guildBanAdd":false,"guildBanRemove":false,"userUpdate":false,"roleCreate":false,"roleDelete":false,"roleUpdate":false,"logChannels":[],"disabledCmds":[],"disabledMdls":[],"disabledAllMdls":false,"blacklistedUsers":[],"badWords":[]},"325464307858931715":{"prefix":"","desc":"","muteRole":"","autoRole":"","selfAssignRoles":[],"joinChanels":[],"joinType":"","joinMsg":"","joinDM":false,"byeChannels":[],"byeType":"","byeMsg":"","byeDM":false,"currency":"","xpSystem":true,"lvlUpMsg":"","channelCreate":false,"channelDelete":false,"channelUpdate":false,"guildBanAdd":false,"guildBanRemove":false,"userUpdate":false,"roleCreate":false,"roleDelete":false,"roleUpdate":false,"logChannels":[],"disabledCmds":[],"disabledMdls":[],"disabledAllMdls":false,"blacklistedUsers":[],"badWords":[]},"351474288483893248":{"prefix":"","desc":"","muteRole":"","autoRole":"","selfAssignRoles":[],"joinChanels":[],"joinType":"","joinMsg":"","joinDM":false,"byeChannels":[],"byeType":"","byeMsg":"","byeDM":false,"currency":"","xpSystem":true,"lvlUpMsg":"","channelCreate":false,"channelDelete":false,"channelUpdate":false,"guildBanAdd":false,"guildBanRemove":false,"userUpdate":false,"roleCreate":false,"roleDelete":false,"roleUpdate":false,"logChannels":[],"disabledCmds":[],"disabledMdls":[],"disabledAllMdls":false,"blacklistedUsers":[],"badWords":[]},"354456771110240268":{"prefix":"","desc":"","muteRole":"","autoRole":"","selfAssignRoles":[],"joinChanels":[],"joinType":"","joinMsg":"","joinDM":false,"byeChannels":[],"byeType":"","byeMsg":"","byeDM":false,"currency":"","xpSystem":true,"lvlUpMsg":"","channelCreate":false,"channelDelete":false,"channelUpdate":false,"guildBanAdd":false,"guildBanRemove":false,"userUpdate":false,"roleCreate":false,"roleDelete":false,"roleUpdate":false,"logChannels":[],"disabledCmds":[],"disabledMdls":[],"disabledAllMdls":false,"blacklistedUsers":[],"badWords":[]},"348906760993636354":{"prefix":"","desc":"","muteRole":"","autoRole":"","selfAssignRoles":[],"joinChanels":[],"joinType":"","joinMsg":"","joinDM":false,"byeChannels":[],"byeType":"","byeMsg":"","byeDM":false,"currency":"","xpSystem":true,"lvlUpMsg":"","channelCreate":false,"channelDelete":false,"channelUpdate":false,"guildBanAdd":false,"guildBanRemove":false,"userUpdate":false,"roleCreate":false,"roleDelete":false,"roleUpdate":false,"logChannels":[],"disabledCmds":[],"disabledMdls":[],"disabledAllMdls":false,"blacklistedUsers":[],"badWords":[]},"237771638274392066":{"prefix":"","desc":"","muteRole":"","autoRole":"","selfAssignRoles":[],"joinChanels":[],"joinType":"","joinMsg":"","joinDM":false,"byeChannels":[],"byeType":"","byeMsg":"","byeDM":false,"currency":"","xpSystem":true,"lvlUpMsg":"","channelCreate":false,"channelDelete":false,"channelUpdate":false,"guildBanAdd":false,"guildBanRemove":false,"userUpdate":false,"roleCreate":false,"roleDelete":false,"roleUpdate":false,"logChannels":[],"disabledCmds":[],"disabledMdls":[],"disabledAllMdls":false,"blacklistedUsers":[],"badWords":[]},"337950174204657675":{"prefix":"","desc":"","muteRole":"","autoRole":"","selfAssignRoles":[],"joinChanels":[],"joinType":"","joinMsg":"","joinDM":false,"byeChannels":[],"byeType":"","byeMsg":"","byeDM":false,"currency":"","xpSystem":true,"lvlUpMsg":"","channelCreate":false,"channelDelete":false,"channelUpdate":false,"guildBanAdd":false,"guildBanRemove":false,"userUpdate":false,"roleCreate":false,"roleDelete":false,"roleUpdate":false,"logChannels":[],"disabledCmds":[],"disabledMdls":[],"disabledAllMdls":false,"blacklistedUsers":[],"badWords":[]},"341235729831297034":{"prefix":"","desc":"","muteRole":"","autoRole":"","selfAssignRoles":[],"joinChanels":[],"joinType":"","joinMsg":"","joinDM":false,"byeChannels":[],"byeType":"","byeMsg":"","byeDM":false,"currency":"","xpSystem":true,"lvlUpMsg":"","channelCreate":false,"channelDelete":false,"channelUpdate":false,"guildBanAdd":false,"guildBanRemove":false,"userUpdate":false,"roleCreate":false,"roleDelete":false,"roleUpdate":false,"logChannels":[],"disabledCmds":[],"disabledMdls":[],"disabledAllMdls":false,"blacklistedUsers":[],"badWords":[]},"361686931995885569":{"prefix":"","desc":"","muteRole":"","autoRole":"","selfAssignRoles":[],"joinChanels":[],"joinType":"","joinMsg":"","joinDM":false,"byeChannels":[],"byeType":"","byeMsg":"","byeDM":false,"currency":"","xpSystem":true,"lvlUpMsg":"","channelCreate":false,"channelDelete":false,"channelUpdate":false,"guildBanAdd":false,"guildBanRemove":false,"userUpdate":false,"roleCreate":false,"roleDelete":false,"roleUpdate":false,"logChannels":[],"disabledCmds":[],"disabledMdls":[],"disabledAllMdls":false,"blacklistedUsers":[],"badWords":[]},"355649620296335360":{"prefix":"","desc":"","muteRole":"","autoRole":"","selfAssignRoles":[],"joinChanels":[],"joinType":"","joinMsg":"","joinDM":false,"byeChannels":[],"byeType":"","byeMsg":"","byeDM":false,"currency":"","xpSystem":true,"lvlUpMsg":"","channelCreate":false,"channelDelete":false,"channelUpdate":false,"guildBanAdd":false,"guildBanRemove":false,"userUpdate":false,"roleCreate":false,"roleDelete":false,"roleUpdate":false,"logChannels":[],"disabledCmds":[],"disabledMdls":[],"disabledAllMdls":false,"blacklistedUsers":[],"badWords":[]},"297982601228976130":{"prefix":"","desc":"","muteRole":"","autoRole":"","selfAssignRoles":[],"joinChanels":[],"joinType":"","joinMsg":"","joinDM":false,"byeChannels":[],"byeType":"","byeMsg":"","byeDM":false,"currency":"","xpSystem":true,"lvlUpMsg":"","channelCreate":false,"channelDelete":false,"channelUpdate":false,"guildBanAdd":false,"guildBanRemove":false,"userUpdate":false,"roleCreate":false,"roleDelete":false,"roleUpdate":false,"logChannels":[],"disabledCmds":[],"disabledMdls":[],"disabledAllMdls":false,"blacklistedUsers":[],"badWords":[]},"360091962407256074":{"prefix":"","desc":"","muteRole":"","autoRole":"","selfAssignRoles":[],"joinChanels":[],"joinType":"","joinMsg":"","joinDM":false,"byeChannels":[],"byeType":"","byeMsg":"","byeDM":false,"currency":"","xpSystem":true,"lvlUpMsg":"","channelCreate":false,"channelDelete":false,"channelUpdate":false,"guildBanAdd":false,"guildBanRemove":false,"userUpdate":false,"roleCreate":false,"roleDelete":false,"roleUpdate":false,"logChannels":[],"disabledCmds":[],"disabledMdls":[],"disabledAllMdls":false,"blacklistedUsers":[],"badWords":[]}}